asdf_cy/__init__.py
asdf_cy/test.c
asdf_cy/test.cpp
asdf_cy/test.pyx
asdf_cy/test.cpython-38-x86_64-linux-gnu.so
asdf_cy/build.py
asdf_cy-0.1.0.dist-info/WHEEL
asdf_cy-0.1.0.dist-info/METADATA
asdf_cy-0.1.0.dist-info/RECORD
