Metadata-Version: 2.1
Name: asdf-cy
Version: 0.1.0
Summary: 
Author: reona
Author-email: c0116129a7@edu.teu.ac.jp
Requires-Python: >=3.8,<3.11
Classifier: Programming Language :: Python :: 3
Classifier: Programming Language :: Python :: 3.10
Classifier: Programming Language :: Python :: 3.8
Classifier: Programming Language :: Python :: 3.9
Requires-Dist: Cython (>=0.29.24,<0.30.0)
Requires-Dist: numpy (>=1.21.4,<2.0.0)
